{
  "drivers": [
    {
      "id": 0,
      "driver": "xone",
      "icon": "input-gaming",
      "experimental": false,
      "removable": true,
      "detection": "lsusb | grep -i xbox"
    },
    {
      "id": 1,
      "driver": "rocm-meta",
      "icon": "amd",
      "experimental": false,
      "removable": true,
      "detection": "lspci -D | grep -iE 'VGA|3D' | grep -i amd"
    },
    {
      "id": 2,
      "driver": "nvidia-driver",
      "icon": "nvidia",
      "experimental": false,
      "removable": true,
      "detection": "lspci -D | grep -iE 'VGA|3D' | grep -i nvidia"
    },
    {
      "id": 3,
      "driver": "alsa-firmware",
      "icon": "speaker",
      "experimental": true,
      "removable": true,
      "detection": "lspci -D | grep -iE 'Audio' | grep -i 'Sound Blaster'"
    }
  ]
}
